MANIFEST.in
README.rst
setup.cfg
setup.py
Encry/Encry.py
Encry/__init__.py
Encry.egg-info/PKG-INFO
Encry.egg-info/SOURCES.txt
Encry.egg-info/dependency_links.txt
Encry.egg-info/not-zip-safe
Encry.egg-info/top_level.txt
Encry/encry/config.py
Encry/encry/settings.py