Metadata-Version: 1.1
Name: Encry
Version: 1.3.1
Summary: A simple encryption module meant for running in the command line, and from python
Home-page: encry.cpnerd.koding.io/Encry.py
Author: CPNerd
Author-email: shadow889566@gmail.com
License: MIT
Platform: UNKNOWN
Classifier: Development Status :: 5 - Production/Stable
Classifier: Intended Audience :: Developers
Classifier: Intended Audience :: End Users/Desktop
